RGV/__init__.py
RGV/aws/__init__.py
RGV/aws/aws_functions.py
RGV/maps/__init__.py
RGV/utils/__init__.py
rgv-0.1.0.dist-info/METADATA
rgv-0.1.0.dist-info/WHEEL
rgv-0.1.0.dist-info/top_level.txt
rgv-0.1.0.dist-info/RECORD
